improv/__init__.py
improv/_version.py
improv/actor.py
improv/cli.py
improv/config.py
improv/link.py
improv/nexus.py
improv/replayer.py
improv/store.py
improv/tui.css
improv/tui.py
improv/watcher.py
improv/utils/__init__.py
improv/utils/bad_config.yaml
improv/utils/checks.py
improv/utils/good_config.yaml
improv/utils/reader.py
improv/utils/utils.py
improv-0.2.2.dist-info/LICENSE
improv-0.2.2.dist-info/METADATA
improv-0.2.2.dist-info/WHEEL
improv-0.2.2.dist-info/entry_points.txt
improv-0.2.2.dist-info/top_level.txt
improv-0.2.2.dist-info/RECORD
