Metadata-Version: 2.1
Name: improv
Version: 0.2.2
Summary: Platform for adaptive neuroscience experiments
Author-email: Anne Draelos <adraelos@umich.edu>, John Pearson <john.pearson@duke.edu>
License: MIT License
Keywords: neuroscience,adaptive,closed loop
Classifier: Development Status :: 3 - Alpha
Classifier: Intended Audience :: Science/Research
Classifier: License :: OSI Approved :: MIT License
Classifier: Operating System :: MacOS :: MacOS X
Classifier: Operating System :: Microsoft :: Windows
Classifier: Operating System :: POSIX
Classifier: Programming Language :: Python :: 3.7
Classifier: Programming Language :: Python :: 3.8
Classifier: Programming Language :: Python :: 3.9
Classifier: Programming Language :: Python :: 3.10
Classifier: Programming Language :: Python :: 3.11
Classifier: Programming Language :: Python :: 3.12
Classifier: Programming Language :: Python :: Implementation :: CPython
Requires-Python: >=3.6
License-File: LICENSE
Requires-Dist: numpy
Requires-Dist: scipy
Requires-Dist: matplotlib
Requires-Dist: pyarrow ==9.0.0
Requires-Dist: PyQt5
Requires-Dist: lmdb
Requires-Dist: pyyaml
Requires-Dist: textual ==0.15.0
Requires-Dist: pyzmq
Requires-Dist: psutil
Requires-Dist: h5py
Provides-Extra: docs
Requires-Dist: jupyter-book ; extra == 'docs'
Requires-Dist: sphinx-autoapi ==2.0.1 ; extra == 'docs'
Requires-Dist: astroid ==2.15.5 ; extra == 'docs'
Provides-Extra: lint
Requires-Dist: black ; extra == 'lint'
Requires-Dist: flake8 ; extra == 'lint'
Requires-Dist: Flake8-pyproject ; extra == 'lint'
Requires-Dist: flake8-pytest-style ; extra == 'lint'
Provides-Extra: tests
Requires-Dist: pytest ; extra == 'tests'
Requires-Dist: async-timeout ; extra == 'tests'
Requires-Dist: pytest-asyncio ; extra == 'tests'
Requires-Dist: pytest-cov ; extra == 'tests'
Requires-Dist: scikit-image ; extra == 'tests'
